api/__init__.py
api/asgi.py
api/local.py
api/settings.py
api/urls.py
api/wsgi.py
apistats/__init__.py
apistats/admin.py
apistats/loader.py
apistats/middlewares.py
apistats/models.py
apistats/tests.py
apistats/migrations/0001_initial.py
apistats/migrations/0002_auto_20201008_2203.py
apistats/migrations/0003_apistat_domain.py
apistats/migrations/0004_auto_20201009_1151.py
apistats/migrations/0005_auto_20201009_1242.py
apistats/migrations/__init__.py
djangophysics/__init__.py
djangophysics/settings.example.py
djangophysics/urls.example.py
djangophysics/urls.py
djangophysics/version.py
djangophysics/calculations/__init__.py
djangophysics/calculations/apps.py
djangophysics/calculations/exceptions.py
djangophysics/calculations/models.py
djangophysics/calculations/renderers.py
djangophysics/calculations/serializers.py
djangophysics/calculations/tests.py
djangophysics/calculations/urls.py
djangophysics/calculations/viewsets.py
djangophysics/converters/__init__.py
djangophysics/converters/apps.py
djangophysics/converters/models.py
djangophysics/converters/serializers.py
djangophysics/converters/views.py
djangophysics/core/__init__.py
djangophysics/core/apps.py
djangophysics/core/helpers.py
djangophysics/core/pagination.py
djangophysics/core/serializers.py
djangophysics/core/settings.py
djangophysics/core/fixtures/base_user.json
djangophysics/countries/__init__.py
djangophysics/countries/apps.py
djangophysics/countries/graphql_serializers.py
djangophysics/countries/helpers.py
djangophysics/countries/models.py
djangophysics/countries/permissions.py
djangophysics/countries/serializers.py
djangophysics/countries/settings.py
djangophysics/countries/tests.py
djangophysics/countries/urls.py
djangophysics/countries/views.py
djangophysics/countries/viewsets.py
djangophysics/countries/services/__init__.py
djangophysics/countries/services/google.py
djangophysics/countries/services/pelias.py
djangophysics/countries/tmp/__init__.py
djangophysics/currencies/__init__.py
djangophysics-1.8.0.dist-info/LICENSE
djangophysics-1.8.0.dist-info/METADATA
djangophysics-1.8.0.dist-info/WHEEL
djangophysics-1.8.0.dist-info/top_level.txt
djangophysics-1.8.0.dist-info/RECORD
